idtpy/__init__.py
idtpy/designer.py
idtpy/gdsutils.py
idtpy/model.py
idtpy/shapes.py
idtpy/utils.py
idtpy/version.py
idtpy-0.1.1.dist-info/METADATA
idtpy-0.1.1.dist-info/WHEEL
idtpy-0.1.1.dist-info/top_level.txt
idtpy-0.1.1.dist-info/RECORD
