Metadata-Version: 2.1
Name: idtpy
Version: 0.1.1
Summary: Simple Python package for the design and modelling of Interdigital Transducers (IDTs).
Home-page: https://github.com/Junliang-Wang/idtpy
Author: Junliang WANG
Author-email: junliang.wang.w@gmail.com
License: BSD-3-Clause
Platform: UNKNOWN
Classifier: Programming Language :: Python :: 3
Classifier: License :: OSI Approved :: BSD License
Classifier: Operating System :: OS Independent
Classifier: Intended Audience :: Customer Service
Classifier: Intended Audience :: Developers
Classifier: Intended Audience :: Education
Classifier: Intended Audience :: Science/Research
Classifier: Natural Language :: English
Requires-Python: >=3.8
Requires-Dist: numpy (>=1.18)
Requires-Dist: scipy (>=1.7)
Provides-Extra: gdspy
Requires-Dist: gdspy (>=1.6) ; extra == 'gdspy'
Provides-Extra: matplotlib
Requires-Dist: matplotlib (>=3.2) ; extra == 'matplotlib'
Provides-Extra: numpy
Requires-Dist: numpy (>=1.18) ; extra == 'numpy'
Provides-Extra: scipy
Requires-Dist: scipy (>=1.7) ; extra == 'scipy'
